LICENSE
MANIFEST.in
README.md
pyproject.toml
setup.py
kscale_mujoco_viewer.egg-info/PKG-INFO
kscale_mujoco_viewer.egg-info/SOURCES.txt
kscale_mujoco_viewer.egg-info/dependency_links.txt
kscale_mujoco_viewer.egg-info/requires.txt
kscale_mujoco_viewer.egg-info/top_level.txt
ksviewer/__init__.py
ksviewer/callbacks.py
ksviewer/mujoco_viewer.py
ksviewer/py.typed
tests/test_dummy.py